<DOMSymbolItem xmlns:xsi="http://www.w3.org/2001/XMLSchema-instance" xmlns="http://ns.adobe.com/xfl/2008/" name="stuff/Title" itemID="4f416ef2-0000024d" lastModified="1329688473">  <timeline>    <DOMTimeline name="Title">      <layers>        <DOMLayer name="Layer 1" color="#4FFF4F" current="true" isSelected="true">          <frames>            <DOMFrame index="0" keyMode="9728">              <elements>                <DOMStaticText width="545.9" height="61" isSelectable="false">                  <matrix>                    <Matrix tx="2" ty="2"/>                  </matrix>                  <textRuns>                    <DOMTextRun>                      <characters>Gibbet Game</characters>                      <textAttrs>                        <DOMTextAttrs alignment="center" aliasText="false" size="48" bitmapSize="960" face="Chalkduster"/>                      </textAttrs>                    </DOMTextRun>                  </textRuns>                </DOMStaticText>              </elements>            </DOMFrame>          </frames>        </DOMLayer>      </layers>    </DOMTimeline>  </timeline></DOMSymbolItem>