<DOMSymbolItem xmlns:xsi="http://www.w3.org/2001/XMLSchema-instance" xmlns="http://ns.adobe.com/xfl/2008/" name="ScoresAsset" itemID="4f41ba8e-000003fd" linkageExportForAS="true" linkageBaseClass="flash.display.Sprite" linkageClassName="tl.framework.examples.gibbetGame.assets.ScoresAsset" lastModified="1329707931" lastUniqueIdentifier="1" isSpriteSubclass="true">  <timeline>    <DOMTimeline name="ScoresAsset">      <layers>        <DOMLayer name="title" color="#4FFF4F" current="true" isSelected="true" autoNamed="false">          <frames>            <DOMFrame index="0" keyMode="15872">              <elements>                <DOMDynamicText name="resultTextField" width="545.9" height="61" includeOutlines="true" isSelectable="false">                  <matrix>                    <Matrix tx="2" ty="22"/>                  </matrix>                  <textRuns>                    <DOMTextRun>                      <characters>You won!</characters>                      <textAttrs>                        <DOMTextAttrs alignment="center" aliasText="false" size="48" bitmapSize="960" face="Chalkduster"/>                      </textAttrs>                    </DOMTextRun>                  </textRuns>                </DOMDynamicText>                <DOMStaticText width="545.9" height="31" includeOutlines="true" isSelectable="false">                  <matrix>                    <Matrix tx="2" ty="99"/>                  </matrix>                  <textRuns>                    <DOMTextRun>                      <characters>The word was:</characters>                      <textAttrs>                        <DOMTextAttrs alignment="center" aliasText="false" size="24" bitmapSize="480" face="Chalkduster"/>                      </textAttrs>                    </DOMTextRun>                  </textRuns>                </DOMStaticText>                <DOMDynamicText name="wordTextField" width="545.9" height="37" includeOutlines="true" isSelectable="false">                  <matrix>                    <Matrix tx="2" ty="137"/>                  </matrix>                  <textRuns>                    <DOMTextRun>                      <characters>someWord</characters>                      <textAttrs>                        <DOMTextAttrs alignment="center" aliasText="false" size="30" bitmapSize="600" face="Chalkduster" fillColor="#0033FF"/>                      </textAttrs>                    </DOMTextRun>                  </textRuns>                </DOMDynamicText>                <DOMStaticText width="545.9" height="31" includeOutlines="true" isSelectable="false">                  <matrix>                    <Matrix tx="2" ty="201"/>                  </matrix>                  <textRuns>                    <DOMTextRun>                      <characters>And you has used this letters:</characters>                      <textAttrs>                        <DOMTextAttrs alignment="center" aliasText="false" size="24" bitmapSize="480" face="Chalkduster"/>                      </textAttrs>                    </DOMTextRun>                  </textRuns>                </DOMStaticText>                <DOMDynamicText name="lettersTextField" width="545.9" height="31" includeOutlines="true" isSelectable="false">                  <matrix>                    <Matrix tx="2" ty="248"/>                  </matrix>                  <textRuns>                    <DOMTextRun>                      <characters>a,b,c</characters>                      <textAttrs>                        <DOMTextAttrs alignment="center" aliasText="false" size="24" bitmapSize="480" face="Chalkduster" fillColor="#0000FF"/>                      </textAttrs>                    </DOMTextRun>                  </textRuns>                </DOMDynamicText>              </elements>            </DOMFrame>          </frames>        </DOMLayer>        <DOMLayer name="click to replay" color="#9933CC" locked="true" autoNamed="false">          <frames>            <DOMFrame index="0" keyMode="9728">              <elements>                <DOMSymbolInstance libraryItemName="stuff/ClickToStartButton" name="clickToReplayButton" symbolType="button">                  <matrix>                    <Matrix ty="319"/>                  </matrix>                  <transformationPoint>                    <Point x="275" y="22"/>                  </transformationPoint>                </DOMSymbolInstance>              </elements>            </DOMFrame>          </frames>        </DOMLayer>      </layers>    </DOMTimeline>  </timeline></DOMSymbolItem>