<DOMSymbolItem xmlns:xsi="http://www.w3.org/2001/XMLSchema-instance" xmlns="http://ns.adobe.com/xfl/2008/" name="WonnaPlayButton" itemID="4f419710-00000277" symbolType="button" lastModified="1329698810">  <timeline>    <DOMTimeline name="WonnaPlayButton">      <layers>        <DOMLayer name="Layer 1" color="#4FFF4F" current="true" isSelected="true">          <frames>            <DOMFrame index="0" keyMode="9728">              <elements>                <DOMSymbolInstance libraryItemName="WonnaPlayUpAnimation" selected="true" centerPoint3DX="270" centerPoint3DY="32.5">                  <transformationPoint>                    <Point x="270" y="32.5"/>                  </transformationPoint>                </DOMSymbolInstance>              </elements>            </DOMFrame>            <DOMFrame index="1" keyMode="9728">              <elements>                <DOMStaticText selected="true" width="536" height="72" includeOutlines="true" isSelectable="false">                  <matrix>                    <Matrix tx="2" ty="-8"/>                  </matrix>                  <textRuns>                    <DOMTextRun>                      <characters>Wonna play?</characters>                      <textAttrs>                        <DOMTextAttrs alignment="center" aliasText="false" size="56" bitmapSize="1120" face="Chalkduster"/>                      </textAttrs>                    </DOMTextRun>                  </textRuns>                </DOMStaticText>              </elements>            </DOMFrame>            <DOMFrame index="2" keyMode="9728">              <elements>                <DOMStaticText width="536" height="61" includeOutlines="true" isSelectable="false">                  <matrix>                    <Matrix ty="4"/>                  </matrix>                  <textRuns>                    <DOMTextRun>                      <characters>Wonna play?</characters>                      <textAttrs>                        <DOMTextAttrs alignment="center" aliasText="false" size="48" face="Chalkduster"/>                      </textAttrs>                    </DOMTextRun>                  </textRuns>                </DOMStaticText>              </elements>            </DOMFrame>            <DOMFrame index="3" keyMode="9728">              <elements>                <DOMShape>                  <fills>                    <FillStyle index="1">                      <SolidColor/>                    </FillStyle>                  </fills>                  <strokes>                    <StrokeStyle index="1">                      <SolidStroke scaleMode="normal">                        <fill>                          <SolidColor/>                        </fill>                      </SolidStroke>                    </StrokeStyle>                  </strokes>                  <edges>                    <Edge fillStyle1="1" strokeStyle="1" edges="!9099 1660|1960 1660!1960 1660|1960 20!1960 20|9099 20!9099 20|9099 1660"/>                  </edges>                </DOMShape>                <DOMStaticText width="536" height="61" includeOutlines="true" isSelectable="false">                  <matrix>                    <Matrix tx="2" ty="2"/>                  </matrix>                  <textRuns>                    <DOMTextRun>                      <characters>Wonna play?</characters>                      <textAttrs>                        <DOMTextAttrs alignment="center" aliasText="false" size="48" face="Chalkduster"/>                      </textAttrs>                    </DOMTextRun>                  </textRuns>                </DOMStaticText>              </elements>            </DOMFrame>          </frames>        </DOMLayer>      </layers>    </DOMTimeline>  </timeline></DOMSymbolItem>